elkoep_aio_mqtt-0.2.33b31.dist-info/licenses/LICENSE
inelsmqtt/__init__.py
inelsmqtt/const.py
inelsmqtt/discovery.py
inelsmqtt/devices/__init__.py
inelsmqtt/protocols/__init__.py
inelsmqtt/protocols/cu3.py
inelsmqtt/protocols/elanrf.py
inelsmqtt/utils/__init__.py
inelsmqtt/utils/common.py
inelsmqtt/utils/core.py
tests/__init__.py
tests/device_tester.py
tests/test_device.py
tests/test_device_value.py
tests/test_discovery.py
tests/test_inels_mqtt.py
elkoep_aio_mqtt-0.2.33b31.dist-info/METADATA
elkoep_aio_mqtt-0.2.33b31.dist-info/WHEEL
elkoep_aio_mqtt-0.2.33b31.dist-info/top_level.txt
elkoep_aio_mqtt-0.2.33b31.dist-info/RECORD
