Metadata-Version: 2.4
Name: elkoep-aio-mqtt
Version: 0.2.33b31
Summary: Python library for iNELS mqtt protocol
Home-page: https://github.com/epdevlab/elkoep-aio-mqtt
Author: Elko EP s.r.o.
Author-email: epdevlab@gmail.com
License: MIT
Keywords: iNels,Elko EP,Home assistant integration
Classifier: License :: OSI Approved :: MIT License
Classifier: Programming Language :: Python :: 3
Classifier: Programming Language :: Python :: 3.9
License-File: LICENSE
Dynamic: author
Dynamic: author-email
Dynamic: classifier
Dynamic: description
Dynamic: description-content-type
Dynamic: home-page
Dynamic: keywords
Dynamic: license
Dynamic: license-file
Dynamic: summary
